txt2stix/__init__.py
txt2stix/attack_flow.py
txt2stix/bundler.py
txt2stix/common.py
txt2stix/credential_checker.py
txt2stix/extractions.py
txt2stix/indicator.py
txt2stix/lookups.py
txt2stix/retriever.py
txt2stix/stix.py
txt2stix/txt2stix.py
txt2stix/utils.py
txt2stix/ai_extractor/__init__.py
txt2stix/ai_extractor/anthropic.py
txt2stix/ai_extractor/base.py
txt2stix/ai_extractor/deepseek.py
txt2stix/ai_extractor/gemini.py
txt2stix/ai_extractor/openai.py
txt2stix/ai_extractor/openrouter.py
txt2stix/ai_extractor/prompts.py
txt2stix/ai_extractor/utils.py
txt2stix/pattern/__init__.py
txt2stix/pattern/extractors/__init__.py
txt2stix/pattern/extractors/base_extractor.py
txt2stix/pattern/extractors/helper.py
txt2stix/pattern/extractors/card/README.md
txt2stix/pattern/extractors/card/__init__.py
txt2stix/pattern/extractors/card/amex_card_extractor.py
txt2stix/pattern/extractors/card/diners_card_extractor.py
txt2stix/pattern/extractors/card/discover_card_extractor.py
txt2stix/pattern/extractors/card/jcb_card_extractor.py
txt2stix/pattern/extractors/card/master_card_extractor.py
txt2stix/pattern/extractors/card/union_card_extractor.py
txt2stix/pattern/extractors/card/visa_card_extractor.py
txt2stix/pattern/extractors/crypto/__init__.py
txt2stix/pattern/extractors/crypto/btc_extractor.py
txt2stix/pattern/extractors/directory/__init__.py
txt2stix/pattern/extractors/directory/unix_directory_extractor.py
txt2stix/pattern/extractors/directory/unix_file_path_extractor.py
txt2stix/pattern/extractors/directory/windows_directory_path_extractor.py
txt2stix/pattern/extractors/directory/windows_file_path_extractor.py
txt2stix/pattern/extractors/domain/__init__.py
txt2stix/pattern/extractors/domain/domain_extractor.py
txt2stix/pattern/extractors/domain/hostname_extractor.py
txt2stix/pattern/extractors/domain/sub_domain_extractor.py
txt2stix/pattern/extractors/hashes/__init__.py
txt2stix/pattern/extractors/hashes/md5_extractor.py
txt2stix/pattern/extractors/hashes/sha1_extractor.py
txt2stix-1.2.2.dist-info/METADATA
txt2stix-1.2.2.dist-info/WHEEL
txt2stix-1.2.2.dist-info/entry_points.txt
txt2stix-1.2.2.dist-info/licenses/LICENSE
txt2stix-1.2.2.dist-info/RECORD
