Metadata-Version: 2.4
Name: txt2stix
Version: 1.2.2
Summary: txt2stix is a Python script that is designed to identify and extract IoCs and TTPs from text files, identify the relationships between them, convert them to STIX 2.1 objects, and output as a STIX 2.1 bundle.
Project-URL: Homepage, https://github.com/muchdogesec/txt2stix
Project-URL: Issues, https://github.com/muchdogesec/txt2stix/issues
Project-URL: dogesec HQ, https://dogesec.com
Author: dogesec
Maintainer: dogesec
License-File: LICENSE
Classifier: License :: OSI Approved :: Apache Software License
Classifier: Operating System :: OS Independent
Classifier: Programming Language :: Python :: 3
Requires-Python: >=3.9
Requires-Dist: base58>=2.1.1
Requires-Dist: beautifulsoup4>=4.12.3
Requires-Dist: json-repair
Requires-Dist: llama-index-core>=0.14.8
Requires-Dist: llama-index-llms-openai>=0.6.8
Requires-Dist: mistune>=3.0.2
Requires-Dist: pathvalidate>=3.2.0
Requires-Dist: phonenumbers>=8.13.39
Requires-Dist: python-dotenv>=1.0.1
Requires-Dist: requests>=2.32.4
Requires-Dist: schwifty>=2024.6.1
Requires-Dist: stix2-validator
Requires-Dist: stix2extensions>=2.0.1
Requires-Dist: tld>=0.13
Requires-Dist: tldextract>=5.1.2
Requires-Dist: validators>=0.28.3
Provides-Extra: anthropic
Requires-Dist: llama-index-llms-anthropic>=0.9.7; extra == 'anthropic'
Provides-Extra: deepseek
Requires-Dist: llama-index-llms-deepseek>=0.2.2; extra == 'deepseek'
Provides-Extra: gemini
Requires-Dist: llama-index-llms-google-genai>=0.5.0; extra == 'gemini'
Provides-Extra: llms
Requires-Dist: llama-index-llms-anthropic>=0.9.7; extra == 'llms'
Requires-Dist: llama-index-llms-deepseek>=0.2.2; extra == 'llms'
Requires-Dist: llama-index-llms-google-genai>=0.5.0; extra == 'llms'
Requires-Dist: llama-index-llms-openrouter>=0.4.2; extra == 'llms'
Provides-Extra: openrouter
Requires-Dist: llama-index-llms-openrouter>=0.4.2; extra == 'openrouter'
Provides-Extra: tests
Requires-Dist: pytest; extra == 'tests'
Requires-Dist: pytest-cov; extra == 'tests'
Requires-Dist: pytest-subtests; extra == 'tests'
Requires-Dist: python-dateutil; extra == 'tests'
Requires-Dist: requests; extra == 'tests'
